confluence_archiving-0.2.8.dist-info/DESCRIPTION.rst
confluence_archiving-0.2.8.dist-info/METADATA
confluence_archiving-0.2.8.dist-info/RECORD
confluence_archiving-0.2.8.dist-info/WHEEL
confluence_archiving-0.2.8.dist-info/metadata.json
confluence_archiving-0.2.8.dist-info/top_level.txt
midori/__init__.py
midori/archiving/__init__.py
midori/archiving/client.py
midori/archiving/models/__init__.py
midori/archiving/models/contentstatus.py
midori/archiving/models/contentstatusdate.py
tests/models/__init__.py
tests/models/test_contentstatus.py
