Metadata-Version: 2.0
Name: confluence-archiving
Version: 0.2.8
Summary: A simple wrapper around the Confluence archiving plugin by Midoris REST API.
Home-page: https://github.com/DaveTCode/confluence-python-lib
Author: David Tyler
Author-email: davet.code@gmail.com
License: UNKNOWN
Keywords: confluence,archiving
Platform: UNKNOWN
Classifier: Development Status :: 3 - Alpha
Classifier: Intended Audience :: Developers
Classifier: License :: OSI Approved :: MIT License
Classifier: Programming Language :: Python :: 2.7
Classifier: Programming Language :: Python :: 3.5
Classifier: Programming Language :: Python :: 3.6
Requires-Python: >=2.7,!=3.0,!=3.1,!=3.2,!=3.3,!=3.4
Requires-Dist: requests (<3.0.0a0,>=2.18.4)
